{"data":{"DateRange":"Aug 9-11, 2024","EndDate":"2024-08-11","Country":"United States","Location":"Burlington, Kentucky","LocationShort":"Burlington, KY","Divisions":[{"DivisionID":100,"Division":"MPO","DivisionName":"Mixed Pro Open","Players":107,"LayoutAssignments":{"1":680559,"2":680559,"3":680559},"IsPro":true,"ShortName":"Mixed Pro Open","AbbreviatedName":"Mixed Pro Open","LatestRound":"3"},{"DivisionID":105,"Division":"FPO","DivisionName":"Women's Pro Open","Players":44,"LayoutAssignments":{"1":680558,"2":680558,"3":680558},"IsPro":true,"ShortName":"Women's Pro Open","AbbreviatedName":"Women's Pro Open","LatestRound":"3"}],"Finals":"no","HighestCompletedRound":3,"LatestRound":"3","FinalRound":3,"Layouts":[{"LayoutID":680558,"CourseID":25473,"CourseName":"Idlewild","Name":"LWS Open 2024 FPO","Holes":18,"Par":71,"Length":9205,"Units":"Feet","Accuracy":"M","Details":[{"Hole":"H1","Label":"1","Par":4,"Length":638},{"Hole":"H2","Label":"2","Par":4,"Length":509},{"Hole":"H3","Label":"3","Par":4,"Length":656},{"Hole":"H4","Label":"4","Par":5,"Length":722},{"Hole":"H5","Label":"5","Par":3,"Length":334},{"Hole":"H6","Label":"6","Par":4,"Length":555},{"Hole":"H7","Label":"7","Par":4,"Length":400},{"Hole":"H8","Label":"8","Par":5,"Length":576},{"Hole":"H9","Label":"9","Par":3,"Length":258},{"Hole":"H10","Label":"10","Par":3,"Length":368},{"Hole":"H11","Label":"11","Par":3,"Length":192},{"Hole":"H12","Label":"12","Par":4,"Length":564},{"Hole":"H13","Label":"13","Par":4,"Length":584},{"Hole":"H14","Label":"14","Par":4,"Length":556},{"Hole":"H15","Label":"15","Par":4,"Length":387},{"Hole":"H16","Label":"16","Par":5,"Length":969},{"Hole":"H17","Label":"17","Par":3,"Length":287},{"Hole":"H18","Label":"18","Par":5,"Length":650}]},{"LayoutID":680559,"CourseID":25473,"CourseName":"Idlewild","Name":"LWS Open 2024 MPO","Holes":18,"Par":68,"Length":9629,"Units":"Feet","Accuracy":"M","Details":[{"Hole":"H1","Label":"1","Par":4,"Length":638},{"Hole":"H2","Label":"2","Par":4,"Length":601},{"Hole":"H3","Label":"3","Par":4,"Length":656},{"Hole":"H4","Label":"4","Par":4,"Length":722},{"Hole":"H5","Label":"5","Par":3,"Length":432},{"Hole":"H6","Label":"6","Par":4,"Length":555},{"Hole":"H7","Label":"7","Par":4,"Length":484},{"Hole":"H8","Label":"8","Par":4,"Length":576},{"Hole":"H9","Label":"9","Par":3,"Length":258},{"Hole":"H10","Label":"10","Par":3,"Length":368},{"Hole":"H11","Label":"11","Par":3,"Length":242},{"Hole":"H12","Label":"12","Par":4,"Length":564},{"Hole":"H13","Label":"13","Par":4,"Length":584},{"Hole":"H14","Label":"14","Par":4,"Length":556},{"Hole":"H15","Label":"15","Par":4,"Length":487},{"Hole":"H16","Label":"16","Par":5,"Length":969},{"Hole":"H17","Label":"17","Par":3,"Length":287},{"Hole":"H18","Label":"18","Par":4,"Length":650}]},{"LayoutID":682593,"CourseID":25473,"CourseName":"Idlewild","Name":"LWS Open 2024 Playoff FPO","Holes":18,"Par":74,"Length":9927,"Units":"Feet","Accuracy":"M","Details":[{"Hole":"H1","Label":"1","Par":4,"Length":638},{"Hole":"H2","Label":"2","Par":4,"Length":509},{"Hole":"H3","Label":"3","Par":4,"Length":656},{"Hole":"H4","Label":"4","Par":5,"Length":722},{"Hole":"H5","Label":"5","Par":3,"Length":334},{"Hole":"H6","Label":"6","Par":4,"Length":555},{"Hole":"H7","Label":"7","Par":4,"Length":400},{"Hole":"H8","Label":"8","Par":5,"Length":576},{"Hole":"H9","Label":"1","Par":4,"Length":638},{"Hole":"H10","Label":"2","Par":4,"Length":509},{"Hole":"H11","Label":"3","Par":4,"Length":656},{"Hole":"H12","Label":"4","Par":5,"Length":722},{"Hole":"H13","Label":"5","Par":3,"Length":334},{"Hole":"H14","Label":"6","Par":4,"Length":555},{"Hole":"H15","Label":"7","Par":4,"Length":400},{"Hole":"H16","Label":"8","Par":5,"Length":576},{"Hole":"H17","Label":"1","Par":4,"Length":638},{"Hole":"H18","Label":"2","Par":4,"Length":509}]},{"LayoutID":682594,"CourseID":25473,"CourseName":"Idlewild","Name":"LWS Open 2024 Playoff MPO","Holes":18,"Par":70,"Length":10567,"Units":"Feet","Accuracy":"M","Details":[{"Hole":"H1","Label":"1","Par":4,"Length":638},{"Hole":"H2","Label":"2","Par":4,"Length":601},{"Hole":"H3","Label":"3","Par":4,"Length":656},{"Hole":"H4","Label":"4","Par":4,"Length":722},{"Hole":"H5","Label":"5","Par":3,"Length":432},{"Hole":"H6","Label":"6","Par":4,"Length":555},{"Hole":"H7","Label":"7","Par":4,"Length":484},{"Hole":"H8","Label":"8","Par":4,"Length":576},{"Hole":"H9","Label":"1","Par":4,"Length":638},{"Hole":"H10","Label":"2","Par":4,"Length":601},{"Hole":"H11","Label":"3","Par":4,"Length":656},{"Hole":"H12","Label":"4","Par":4,"Length":722},{"Hole":"H13","Label":"5","Par":3,"Length":432},{"Hole":"H14","Label":"6","Par":4,"Length":555},{"Hole":"H15","Label":"7","Par":4,"Length":484},{"Hole":"H16","Label":"8","Par":4,"Length":576},{"Hole":"H17","Label":"1","Par":4,"Length":638},{"Hole":"H18","Label":"2","Par":4,"Length":601}]}],"LayoutIDs":[{"1":680558,"2":680558,"3":680558,"4":0,"5":0,"6":0,"7":0,"8":0,"9":0,"10":0,"11":0,"12":0,"13":680558,"Division":"FPO","Pool":""},{"1":680559,"2":680559,"3":680559,"4":0,"5":0,"6":0,"7":0,"8":0,"9":0,"10":0,"11":0,"12":0,"13":682594,"Division":"MPO","Pool":""}],"Name":"LWS Open at Idlewild presented by Dynamic Discs \u0026 The Nati","NameHtml":"LWS Open at Idlewild presented by Dynamic Discs \u0026amp; The Nati","MultiLineName":{"pre":"","main":"LWS Open at Idlewild","post":"presented by Dynamic Discs \u0026 The Nati"},"MultiLineNameHtml":" \u003cspan class=\"event-name-main\"\u003eLWS Open at Idlewild\u003c/span\u003e \u003cspan class=\"event-name-post\"\u003epresented by Dynamic Discs \u0026amp; The Nati\u003c/span\u003e","RawTier":"ES","Rounds":3,"RoundsList":{"1":{"Number":1,"Label":"Round 1","LabelAbbreviated":"Rd 1","Date":"2024-08-11","DateAbbreviated":"Aug 11","ShowDate":false},"13":{"Number":13,"Label":"Playoff","LabelAbbreviated":"P","Date":"2024-08-11","DateAbbreviated":"Aug 11","ShowDate":false},"2":{"Number":2,"Label":"Round 2","LabelAbbreviated":"Rd 2","Date":"2024-08-11","DateAbbreviated":"Aug 11","ShowDate":false},"3":{"Number":3,"Label":"Round 3","LabelAbbreviated":"Rd 3","Date":"2024-08-11","DateAbbreviated":"Aug 11","ShowDate":false}},"Semis":"no","SimpleName":"DGPT - LWS Open at Idlewild","StartDate":"2024-08-09","TDName":"Adam Jones","TDPDGANum":27655,"Tier":"Disc Golf Pro Tour","FormattedTier":"Disc Golf Pro Tour","FormattedLongTier":"Disc Golf Pro Tour","TierPro":"ES","TierAm":"ES","TierX":false,"TotalPlayers":151,"TournamentId":"77771","International":true,"FullStats":true,"AdditionalEventInfo":{"RoundsList":null,"BroadcastUrl":""}},"hash":"20477c1abf6565a69b0bf72391bba8d3"}