{"data":{"DateRange":"Mar 21-24, 2024","EndDate":"2024-03-24","Country":"United States","Location":"Round Rock, Texas","LocationShort":"Round Rock, TX","Divisions":[{"DivisionID":105,"Division":"FPO","DivisionName":"Women's Pro Open","Players":100,"LayoutAssignments":{"1":662638,"2":664125,"3":662638,"4":664124},"IsPro":true,"ShortName":"Women's Pro Open","AbbreviatedName":"Women's Pro Open","LatestRound":"4"},{"DivisionID":116,"Division":"FP40","DivisionName":"Women's Pro 40+","Players":27,"LayoutAssignments":{"1":662638,"2":664125,"3":662638,"4":664124},"IsPro":true,"ShortName":"Women's Pro 40+","AbbreviatedName":"Women's Pro 40+","LatestRound":"4"},{"DivisionID":126,"Division":"FP50","DivisionName":"Women's Pro 50+","Players":8,"LayoutAssignments":{"1":662640,"2":662640,"3":662640,"4":664123},"IsPro":true,"ShortName":"Women's Pro 50+","AbbreviatedName":"Women's Pro 50+","LatestRound":"4"},{"DivisionID":136,"Division":"FP55","DivisionName":"Women's Pro 55+","Players":9,"LayoutAssignments":{"1":662640,"2":662640,"3":662640,"4":664123},"IsPro":true,"ShortName":"Women's Pro 55+","AbbreviatedName":"Women's Pro 55+","LatestRound":"4"},{"DivisionID":146,"Division":"FP60","DivisionName":"Women's Pro 60+","Players":6,"LayoutAssignments":{"1":662640,"2":662640,"3":662640,"4":664123},"IsPro":true,"ShortName":"Women's Pro 60+","AbbreviatedName":"Women's Pro 60+","LatestRound":"4"},{"DivisionID":156,"Division":"FP65","DivisionName":"Women's Pro 65+","Players":8,"LayoutAssignments":{"1":662640,"2":662640,"3":662640,"4":664123},"IsPro":true,"ShortName":"Women's Pro 65+","AbbreviatedName":"Women's Pro 65+","LatestRound":"4"},{"DivisionID":166,"Division":"FP70","DivisionName":"Women's Pro 70+","Players":3,"LayoutAssignments":{"1":662629,"2":662629,"3":662639,"4":662639},"IsPro":true,"ShortName":"Women's Pro 70+","AbbreviatedName":"Women's Pro 70+","LatestRound":"4"},{"DivisionID":176,"Division":"FP75","DivisionName":"Women's Pro 75+","Players":3,"LayoutAssignments":{"1":662629,"2":662629,"3":662639,"4":662639},"IsPro":true,"ShortName":"Women's Pro 75+","AbbreviatedName":"Women's Pro 75+","LatestRound":"4"},{"DivisionID":405,"Division":"FA1","DivisionName":"Women's Amateur 1","Players":42,"LayoutAssignments":{"1":662640,"2":662640,"3":662640,"4":664123},"IsPro":false,"ShortName":"Women's Amateur 1","AbbreviatedName":"Women's Am 1","LatestRound":"4"},{"DivisionID":416,"Division":"FA40","DivisionName":"Women's Amateur 40+","Players":8,"LayoutAssignments":{"1":662640,"2":662640,"3":662640,"4":664123},"IsPro":false,"ShortName":"Women's Amateur 40+","AbbreviatedName":"Women's Am 40+","LatestRound":"4"},{"DivisionID":426,"Division":"FA50","DivisionName":"Women's Amateur 50+","Players":16,"LayoutAssignments":{"1":662634,"2":662634,"3":662628,"4":662628},"IsPro":false,"ShortName":"Women's Amateur 50+","AbbreviatedName":"Women's Am 50+","LatestRound":"4"},{"DivisionID":436,"Division":"FA55","DivisionName":"Women's Amateur 55+","Players":4,"LayoutAssignments":{"1":662634,"2":662634,"3":662628,"4":662628},"IsPro":false,"ShortName":"Women's Amateur 55+","AbbreviatedName":"Women's Am 55+","LatestRound":"4"},{"DivisionID":446,"Division":"FA60","DivisionName":"Women's Amateur 60+","Players":8,"LayoutAssignments":{"1":662634,"2":662634,"3":662628,"4":662628},"IsPro":false,"ShortName":"Women's Amateur 60+","AbbreviatedName":"Women's Am 60+","LatestRound":"4"},{"DivisionID":466,"Division":"FA70","DivisionName":"Women's Amateur 70+","Players":3,"LayoutAssignments":{"1":662629,"2":662629,"3":662639,"4":662639},"IsPro":false,"ShortName":"Women's Amateur 70+","AbbreviatedName":"Women's Am 70+","LatestRound":"4"},{"DivisionID":505,"Division":"FA2","DivisionName":"Women's Amateur 2","Players":39,"LayoutAssignments":{"1":662634,"2":662634,"3":662628,"4":662628},"IsPro":false,"ShortName":"Women's Amateur 2","AbbreviatedName":"Women's Am 2","LatestRound":"4"},{"DivisionID":605,"Division":"FA3","DivisionName":"Women's Amateur 3","Players":17,"LayoutAssignments":{"1":662629,"2":662629,"3":662639,"4":662639},"IsPro":false,"ShortName":"Women's Amateur 3","AbbreviatedName":"Women's Am 3","LatestRound":"4"},{"DivisionID":705,"Division":"FA4","DivisionName":"Women's Amateur 4","Players":20,"LayoutAssignments":{"1":662629,"2":662629,"3":662639,"4":662639},"IsPro":false,"ShortName":"Women's Amateur 4","AbbreviatedName":"Women's Am 4","LatestRound":"4"},{"DivisionID":806,"Division":"FJ18","DivisionName":"Girls' Junior ≤18","Players":3,"LayoutAssignments":{"1":662629,"2":662629,"3":662639,"4":662639},"IsPro":false,"ShortName":"Girls' Junior ≤18","AbbreviatedName":"Girls' Junior ≤18","LatestRound":"4"},{"DivisionID":816,"Division":"FJ15","DivisionName":"Girls' Junior ≤15","Players":10,"LayoutAssignments":{"1":662629,"2":662629,"3":662639,"4":662639},"IsPro":false,"ShortName":"Girls' Junior ≤15","AbbreviatedName":"Girls' Junior ≤15","LatestRound":"4"},{"DivisionID":826,"Division":"FJ12","DivisionName":"Girls' Junior ≤12","Players":8,"LayoutAssignments":{"1":662629,"2":662629,"3":662639,"4":662639},"IsPro":false,"ShortName":"Girls' Junior ≤12","AbbreviatedName":"Girls' Junior ≤12","LatestRound":"4"},{"DivisionID":836,"Division":"FJ10","DivisionName":"Girls' Junior ≤10","Players":4,"LayoutAssignments":{"1":662629,"2":662629,"3":662639,"4":662639},"IsPro":false,"ShortName":"Girls' Junior ≤10","AbbreviatedName":"Girls' Junior ≤10","LatestRound":"4"}],"Finals":"no","HighestCompletedRound":13,"LatestRound":"4","FinalRound":4,"Layouts":[{"LayoutID":655023,"CourseID":-1,"CourseName":"","Name":"Default Layout","Holes":18,"Par":54,"Length":5000,"Units":"Feet","Accuracy":"M","Details":[{"Hole":"H1","Label":"1","Par":3,"Length":null},{"Hole":"H2","Label":"2","Par":3,"Length":null},{"Hole":"H3","Label":"3","Par":3,"Length":null},{"Hole":"H4","Label":"4","Par":3,"Length":null},{"Hole":"H5","Label":"5","Par":3,"Length":null},{"Hole":"H6","Label":"6","Par":3,"Length":null},{"Hole":"H7","Label":"7","Par":3,"Length":null},{"Hole":"H8","Label":"8","Par":3,"Length":null},{"Hole":"H9","Label":"9","Par":3,"Length":null},{"Hole":"H10","Label":"10","Par":3,"Length":null},{"Hole":"H11","Label":"11","Par":3,"Length":null},{"Hole":"H12","Label":"12","Par":3,"Length":null},{"Hole":"H13","Label":"13","Par":3,"Length":null},{"Hole":"H14","Label":"14","Par":3,"Length":null},{"Hole":"H15","Label":"15","Par":3,"Length":null},{"Hole":"H16","Label":"16","Par":3,"Length":null},{"Hole":"H17","Label":"17","Par":3,"Length":null},{"Hole":"H18","Label":"18","Par":3,"Length":null}]},{"LayoutID":662628,"CourseID":26745,"CourseName":"Benbrook Ranch Park","Name":"Benbrook 24 USWDGC","Holes":18,"Par":63,"Length":6785,"Units":"Feet","Accuracy":"M","Details":[{"Hole":"H1","Label":"1","Par":4,"Length":480},{"Hole":"H2","Label":"2","Par":3,"Length":280},{"Hole":"H3","Label":"3","Par":3,"Length":240},{"Hole":"H4","Label":"4","Par":4,"Length":555},{"Hole":"H5","Label":"5","Par":5,"Length":610},{"Hole":"H6","Label":"6","Par":3,"Length":240},{"Hole":"H7","Label":"7","Par":3,"Length":310},{"Hole":"H8","Label":"8","Par":3,"Length":315},{"Hole":"H9","Label":"9","Par":3,"Length":255},{"Hole":"H10","Label":"10","Par":4,"Length":505},{"Hole":"H11","Label":"11","Par":3,"Length":225},{"Hole":"H12","Label":"12","Par":4,"Length":440},{"Hole":"H13","Label":"13","Par":3,"Length":265},{"Hole":"H14","Label":"14","Par":3,"Length":230},{"Hole":"H15","Label":"15","Par":5,"Length":640},{"Hole":"H16","Label":"16","Par":3,"Length":305},{"Hole":"H17","Label":"17","Par":3,"Length":345},{"Hole":"H18","Label":"18","Par":4,"Length":545}]},{"LayoutID":662629,"CourseID":240291,"CourseName":"Live Oak","Name":"Live Oak 24 USWDGC","Holes":18,"Par":57,"Length":4730,"Units":"Feet","Accuracy":"M","Details":[{"Hole":"H1","Label":"1","Par":3,"Length":240},{"Hole":"H2","Label":"2","Par":4,"Length":384},{"Hole":"H3","Label":"3","Par":3,"Length":263},{"Hole":"H4","Label":"4","Par":3,"Length":334},{"Hole":"H5","Label":"5","Par":3,"Length":254},{"Hole":"H6","Label":"6","Par":3,"Length":205},{"Hole":"H7","Label":"7","Par":3,"Length":198},{"Hole":"H8","Label":"8","Par":3,"Length":237},{"Hole":"H9","Label":"9","Par":3,"Length":312},{"Hole":"H10","Label":"10","Par":3,"Length":279},{"Hole":"H11","Label":"11","Par":3,"Length":225},{"Hole":"H12","Label":"12","Par":3,"Length":147},{"Hole":"H13","Label":"13","Par":5,"Length":528},{"Hole":"H14","Label":"14","Par":3,"Length":172},{"Hole":"H15","Label":"15","Par":3,"Length":248},{"Hole":"H16","Label":"16","Par":3,"Length":176},{"Hole":"H17","Label":"17","Par":3,"Length":280},{"Hole":"H18","Label":"18","Par":3,"Length":248}]},{"LayoutID":662634,"CourseID":25373,"CourseName":"Old Settlers' Park","Name":"Settlers 24 USWDGC","Holes":18,"Par":62,"Length":6082,"Units":"Feet","Accuracy":"M","Details":[{"Hole":"H1","Label":"1","Par":3,"Length":252},{"Hole":"H2","Label":"2","Par":3,"Length":264},{"Hole":"H3","Label":"3","Par":3,"Length":289},{"Hole":"H4","Label":"4","Par":4,"Length":444},{"Hole":"H5","Label":"5","Par":3,"Length":183},{"Hole":"H6","Label":"6","Par":3,"Length":285},{"Hole":"H7","Label":"7","Par":5,"Length":564},{"Hole":"H8","Label":"8","Par":3,"Length":244},{"Hole":"H9","Label":"9","Par":3,"Length":293},{"Hole":"H10","Label":"10","Par":4,"Length":575},{"Hole":"H11","Label":"11","Par":4,"Length":368},{"Hole":"H12","Label":"12","Par":3,"Length":274},{"Hole":"H13","Label":"13","Par":3,"Length":200},{"Hole":"H14","Label":"14","Par":3,"Length":250},{"Hole":"H15","Label":"15","Par":5,"Length":570},{"Hole":"H16","Label":"16","Par":3,"Length":220},{"Hole":"H17","Label":"17","Par":3,"Length":242},{"Hole":"H18","Label":"18","Par":4,"Length":565}]},{"LayoutID":662638,"CourseID":303867,"CourseName":"Sprinkle Valley","Name":"Sprinkle 24 USWDGC","Holes":18,"Par":65,"Length":8315,"Units":"Feet","Accuracy":"M","Details":[{"Hole":"H1","Label":"1","Par":4,"Length":570},{"Hole":"H2","Label":"2","Par":4,"Length":516},{"Hole":"H3","Label":"3","Par":3,"Length":300},{"Hole":"H4","Label":"4","Par":3,"Length":360},{"Hole":"H5","Label":"5","Par":4,"Length":450},{"Hole":"H6","Label":"6","Par":3,"Length":306},{"Hole":"H7","Label":"7","Par":4,"Length":640},{"Hole":"H8","Label":"8","Par":3,"Length":300},{"Hole":"H9","Label":"9","Par":4,"Length":470},{"Hole":"H10","Label":"10","Par":3,"Length":290},{"Hole":"H11","Label":"11","Par":4,"Length":623},{"Hole":"H12","Label":"12","Par":3,"Length":330},{"Hole":"H13","Label":"13","Par":4,"Length":580},{"Hole":"H14","Label":"14","Par":3,"Length":280},{"Hole":"H15","Label":"15","Par":4,"Length":590},{"Hole":"H16","Label":"16","Par":4,"Length":650},{"Hole":"H17","Label":"17","Par":3,"Length":280},{"Hole":"H18","Label":"18","Par":5,"Length":780}]},{"LayoutID":662639,"CourseID":25333,"CourseName":"Wells Branch Park","Name":"Wells 24 USWDGC","Holes":18,"Par":54,"Length":3873,"Units":"Feet","Accuracy":"M","Details":[{"Hole":"H1","Label":"1","Par":3,"Length":241},{"Hole":"H2","Label":"2","Par":3,"Length":200},{"Hole":"H3","Label":"3","Par":3,"Length":230},{"Hole":"H4","Label":"4","Par":3,"Length":180},{"Hole":"H5","Label":"5","Par":3,"Length":173},{"Hole":"H6","Label":"6","Par":3,"Length":251},{"Hole":"H7","Label":"7","Par":3,"Length":250},{"Hole":"H8","Label":"8","Par":3,"Length":133},{"Hole":"H9","Label":"9","Par":3,"Length":186},{"Hole":"H10","Label":"10","Par":3,"Length":188},{"Hole":"H11","Label":"11","Par":3,"Length":164},{"Hole":"H12","Label":"12","Par":3,"Length":222},{"Hole":"H13","Label":"13","Par":3,"Length":115},{"Hole":"H14","Label":"14","Par":3,"Length":260},{"Hole":"H15","Label":"15","Par":3,"Length":305},{"Hole":"H16","Label":"16","Par":3,"Length":274},{"Hole":"H17","Label":"17","Par":3,"Length":186},{"Hole":"H18","Label":"18","Par":3,"Length":315}]},{"LayoutID":662640,"CourseID":26443,"CourseName":"Williamson County","Name":"Wilco 24 USWDGC","Holes":18,"Par":59,"Length":6254,"Units":"Feet","Accuracy":"M","Details":[{"Hole":"H1","Label":"1","Par":3,"Length":255},{"Hole":"H2","Label":"2","Par":4,"Length":600},{"Hole":"H3","Label":"3","Par":4,"Length":545},{"Hole":"H4","Label":"4","Par":3,"Length":215},{"Hole":"H5","Label":"5","Par":3,"Length":285},{"Hole":"H6","Label":"6","Par":3,"Length":275},{"Hole":"H7","Label":"7","Par":3,"Length":325},{"Hole":"H8","Label":"8","Par":3,"Length":210},{"Hole":"H9","Label":"9","Par":4,"Length":363},{"Hole":"H10","Label":"10","Par":3,"Length":205},{"Hole":"H11","Label":"11","Par":3,"Length":240},{"Hole":"H12","Label":"12","Par":3,"Length":230},{"Hole":"H13","Label":"13","Par":4,"Length":560},{"Hole":"H14","Label":"14","Par":3,"Length":350},{"Hole":"H15","Label":"15","Par":3,"Length":396},{"Hole":"H16","Label":"16","Par":3,"Length":360},{"Hole":"H17","Label":"17","Par":4,"Length":550},{"Hole":"H18","Label":"18","Par":3,"Length":290}]},{"LayoutID":663298,"CourseID":303867,"CourseName":"Sprinkle Valley","Name":"Sprinkle Valley Playoff","Holes":18,"Par":66,"Length":8859,"Units":"Feet","Accuracy":"M","Details":[{"Hole":"H1","Label":"10","Par":3,"Length":290},{"Hole":"H2","Label":"11","Par":4,"Length":623},{"Hole":"H3","Label":"12","Par":3,"Length":330},{"Hole":"H4","Label":"16","Par":4,"Length":650},{"Hole":"H5","Label":"17","Par":3,"Length":280},{"Hole":"H6","Label":"18","Par":5,"Length":780},{"Hole":"H7","Label":"10","Par":3,"Length":290},{"Hole":"H8","Label":"11","Par":4,"Length":623},{"Hole":"H9","Label":"12","Par":3,"Length":330},{"Hole":"H10","Label":"16","Par":4,"Length":650},{"Hole":"H11","Label":"17","Par":3,"Length":280},{"Hole":"H12","Label":"18","Par":5,"Length":780},{"Hole":"H13","Label":"10","Par":3,"Length":290},{"Hole":"H14","Label":"11","Par":4,"Length":623},{"Hole":"H15","Label":"12","Par":3,"Length":330},{"Hole":"H16","Label":"16","Par":4,"Length":650},{"Hole":"H17","Label":"17","Par":3,"Length":280},{"Hole":"H18","Label":"18","Par":5,"Length":780}]},{"LayoutID":664123,"CourseID":26443,"CourseName":"Williamson County","Name":"Wilco 24 USWDGC Rd4","Holes":18,"Par":59,"Length":6254,"Units":"Feet","Accuracy":"M","Details":[{"Hole":"H1","Label":"1","Par":3,"Length":255},{"Hole":"H2","Label":"2","Par":4,"Length":600},{"Hole":"H3","Label":"3","Par":4,"Length":545},{"Hole":"H4","Label":"4","Par":3,"Length":215},{"Hole":"H5","Label":"5","Par":3,"Length":285},{"Hole":"H6","Label":"6","Par":3,"Length":275},{"Hole":"H7","Label":"7","Par":3,"Length":325},{"Hole":"H8","Label":"8","Par":3,"Length":210},{"Hole":"H9","Label":"9","Par":4,"Length":363},{"Hole":"H10","Label":"10","Par":3,"Length":205},{"Hole":"H11","Label":"11","Par":3,"Length":240},{"Hole":"H12","Label":"12","Par":3,"Length":230},{"Hole":"H13","Label":"13","Par":4,"Length":560},{"Hole":"H14","Label":"14","Par":3,"Length":350},{"Hole":"H15","Label":"15","Par":3,"Length":396},{"Hole":"H16","Label":"16","Par":3,"Length":360},{"Hole":"H17","Label":"17","Par":4,"Length":550},{"Hole":"H18","Label":"18","Par":3,"Length":290}]},{"LayoutID":664124,"CourseID":303867,"CourseName":"Sprinkle Valley","Name":"Sprinkle 24 USWDGC Rd4","Holes":18,"Par":65,"Length":8315,"Units":"Feet","Accuracy":"M","Details":[{"Hole":"H1","Label":"1","Par":4,"Length":570},{"Hole":"H2","Label":"2","Par":4,"Length":516},{"Hole":"H3","Label":"3","Par":3,"Length":300},{"Hole":"H4","Label":"4","Par":3,"Length":360},{"Hole":"H5","Label":"5","Par":4,"Length":450},{"Hole":"H6","Label":"6","Par":3,"Length":306},{"Hole":"H7","Label":"7","Par":4,"Length":640},{"Hole":"H8","Label":"8","Par":3,"Length":300},{"Hole":"H9","Label":"9","Par":4,"Length":470},{"Hole":"H10","Label":"10","Par":3,"Length":290},{"Hole":"H11","Label":"11","Par":4,"Length":623},{"Hole":"H12","Label":"12","Par":3,"Length":330},{"Hole":"H13","Label":"13","Par":4,"Length":580},{"Hole":"H14","Label":"14","Par":3,"Length":280},{"Hole":"H15","Label":"15","Par":4,"Length":590},{"Hole":"H16","Label":"16","Par":4,"Length":650},{"Hole":"H17","Label":"17","Par":3,"Length":280},{"Hole":"H18","Label":"18","Par":5,"Length":780}]},{"LayoutID":664125,"CourseID":303867,"CourseName":"Sprinkle Valley","Name":"Sprinkle 24 USWDGC Rd2","Holes":18,"Par":65,"Length":8315,"Units":"Feet","Accuracy":"M","Details":[{"Hole":"H1","Label":"1","Par":4,"Length":570},{"Hole":"H2","Label":"2","Par":4,"Length":516},{"Hole":"H3","Label":"3","Par":3,"Length":300},{"Hole":"H4","Label":"4","Par":3,"Length":360},{"Hole":"H5","Label":"5","Par":4,"Length":450},{"Hole":"H6","Label":"6","Par":3,"Length":306},{"Hole":"H7","Label":"7","Par":4,"Length":640},{"Hole":"H8","Label":"8","Par":3,"Length":300},{"Hole":"H9","Label":"9","Par":4,"Length":470},{"Hole":"H10","Label":"10","Par":3,"Length":290},{"Hole":"H11","Label":"11","Par":4,"Length":623},{"Hole":"H12","Label":"12","Par":3,"Length":330},{"Hole":"H13","Label":"13","Par":4,"Length":580},{"Hole":"H14","Label":"14","Par":3,"Length":280},{"Hole":"H15","Label":"15","Par":4,"Length":590},{"Hole":"H16","Label":"16","Par":4,"Length":650},{"Hole":"H17","Label":"17","Par":3,"Length":280},{"Hole":"H18","Label":"18","Par":5,"Length":780}]}],"LayoutIDs":[{"1":662640,"2":662640,"3":662640,"4":664123,"5":0,"6":0,"7":0,"8":0,"9":0,"10":0,"11":0,"12":0,"13":662640,"Division":"FA1","Pool":""},{"1":662634,"2":662634,"3":662628,"4":662628,"5":0,"6":0,"7":0,"8":0,"9":0,"10":0,"11":0,"12":0,"13":662628,"Division":"FA2","Pool":""},{"1":662629,"2":662629,"3":662639,"4":662639,"5":0,"6":0,"7":0,"8":0,"9":0,"10":0,"11":0,"12":0,"13":662639,"Division":"FA3","Pool":""},{"1":662629,"2":662629,"3":662639,"4":662639,"5":0,"6":0,"7":0,"8":0,"9":0,"10":0,"11":0,"12":0,"13":662639,"Division":"FA4","Pool":""},{"1":662640,"2":662640,"3":662640,"4":664123,"5":0,"6":0,"7":0,"8":0,"9":0,"10":0,"11":0,"12":0,"13":662640,"Division":"FA40","Pool":""},{"1":662634,"2":662634,"3":662628,"4":662628,"5":0,"6":0,"7":0,"8":0,"9":0,"10":0,"11":0,"12":0,"13":662628,"Division":"FA50","Pool":""},{"1":662634,"2":662634,"3":662628,"4":662628,"5":0,"6":0,"7":0,"8":0,"9":0,"10":0,"11":0,"12":0,"13":662628,"Division":"FA55","Pool":""},{"1":662634,"2":662634,"3":662628,"4":662628,"5":0,"6":0,"7":0,"8":0,"9":0,"10":0,"11":0,"12":0,"13":662628,"Division":"FA60","Pool":""},{"1":655023,"2":655023,"3":655023,"4":655023,"5":0,"6":0,"7":0,"8":0,"9":0,"10":0,"11":0,"12":0,"13":655023,"Division":"FA65","Pool":""},{"1":662629,"2":662629,"3":662639,"4":662639,"5":0,"6":0,"7":0,"8":0,"9":0,"10":0,"11":0,"12":0,"13":662639,"Division":"FA70","Pool":""},{"1":655023,"2":655023,"3":655023,"4":655023,"5":0,"6":0,"7":0,"8":0,"9":0,"10":0,"11":0,"12":0,"13":655023,"Division":"FA75","Pool":""},{"1":655023,"2":655023,"3":655023,"4":655023,"5":0,"6":0,"7":0,"8":0,"9":0,"10":0,"11":0,"12":0,"13":655023,"Division":"FJ08","Pool":""},{"1":662629,"2":662629,"3":662639,"4":662639,"5":0,"6":0,"7":0,"8":0,"9":0,"10":0,"11":0,"12":0,"13":662639,"Division":"FJ10","Pool":""},{"1":662629,"2":662629,"3":662639,"4":662639,"5":0,"6":0,"7":0,"8":0,"9":0,"10":0,"11":0,"12":0,"13":662639,"Division":"FJ12","Pool":""},{"1":662629,"2":662629,"3":662639,"4":662639,"5":0,"6":0,"7":0,"8":0,"9":0,"10":0,"11":0,"12":0,"13":662639,"Division":"FJ15","Pool":""},{"1":662629,"2":662629,"3":662639,"4":662639,"5":0,"6":0,"7":0,"8":0,"9":0,"10":0,"11":0,"12":0,"13":662639,"Division":"FJ18","Pool":""},{"1":662638,"2":664125,"3":662638,"4":664124,"5":0,"6":0,"7":0,"8":0,"9":0,"10":0,"11":0,"12":0,"13":662638,"Division":"FP40","Pool":""},{"1":662640,"2":662640,"3":662640,"4":664123,"5":0,"6":0,"7":0,"8":0,"9":0,"10":0,"11":0,"12":0,"13":662640,"Division":"FP50","Pool":""},{"1":662640,"2":662640,"3":662640,"4":664123,"5":0,"6":0,"7":0,"8":0,"9":0,"10":0,"11":0,"12":0,"13":662640,"Division":"FP55","Pool":""},{"1":662640,"2":662640,"3":662640,"4":664123,"5":0,"6":0,"7":0,"8":0,"9":0,"10":0,"11":0,"12":0,"13":662640,"Division":"FP60","Pool":""},{"1":662640,"2":662640,"3":662640,"4":664123,"5":0,"6":0,"7":0,"8":0,"9":0,"10":0,"11":0,"12":0,"13":662640,"Division":"FP65","Pool":""},{"1":662629,"2":662629,"3":662639,"4":662639,"5":0,"6":0,"7":0,"8":0,"9":0,"10":0,"11":0,"12":0,"13":662639,"Division":"FP70","Pool":""},{"1":662629,"2":662629,"3":662639,"4":662639,"5":0,"6":0,"7":0,"8":0,"9":0,"10":0,"11":0,"12":0,"13":662639,"Division":"FP75","Pool":""},{"1":662638,"2":664125,"3":662638,"4":664124,"5":0,"6":0,"7":0,"8":0,"9":0,"10":0,"11":0,"12":0,"13":662638,"Division":"FPO","Pool":""}],"Name":"2024 United States Women's Disc Golf Championships presented by Mint Discs","NameHtml":"2024 United States Women's Disc Golf Championships presented by Mint Discs","MultiLineName":{"pre":"","main":"2024 United States Women's Disc Golf Championships","post":"presented by Mint Discs"},"MultiLineNameHtml":" \u003cspan class=\"event-name-main\"\u003e2024 United States Women's Disc Golf Championships\u003c/span\u003e \u003cspan class=\"event-name-post\"\u003epresented by Mint Discs\u003c/span\u003e","RawTier":"M","Rounds":4,"RoundsList":{"1":{"Number":1,"Label":"Round 1","LabelAbbreviated":"Rd 1","Date":"2024-03-24","DateAbbreviated":"Mar 24","ShowDate":false},"13":{"Number":13,"Label":"Playoff","LabelAbbreviated":"P","Date":"2024-03-24","DateAbbreviated":"Mar 24","ShowDate":false},"2":{"Number":2,"Label":"Round 2","LabelAbbreviated":"Rd 2","Date":"2024-03-24","DateAbbreviated":"Mar 24","ShowDate":false},"3":{"Number":3,"Label":"Round 3","LabelAbbreviated":"Rd 3","Date":"2024-03-24","DateAbbreviated":"Mar 24","ShowDate":false},"4":{"Number":4,"Label":"Round 4","LabelAbbreviated":"Rd 4","Date":"2024-03-24","DateAbbreviated":"Mar 24","ShowDate":false}},"Semis":"no","SimpleName":"2024 United States Women's Disc Golf Championships","StartDate":"2024-03-21","TDName":"Zachery Jansen","TDPDGANum":39386,"Tier":"Major","FormattedTier":"Major","FormattedLongTier":"Major","TierPro":"M","TierAm":"M","TierX":false,"TotalPlayers":346,"TournamentId":"77091","International":true,"FullStats":true,"AdditionalEventInfo":{"RoundsList":null,"BroadcastUrl":""}},"hash":"b4bc4314562430eb06dc8554a2b1368d"}