{"data":{"DateRange":"Jun 7-9, 2024","EndDate":"2024-06-09","Country":"Finland","Location":"Heinola, Finland","LocationShort":"Heinola, Finland","Divisions":[{"DivisionID":100,"Division":"MPO","DivisionName":"Mixed Pro Open","Players":108,"LayoutAssignments":{"1":657746,"2":657746,"3":657746},"IsPro":true,"ShortName":"Mixed Pro Open","AbbreviatedName":"Mixed Pro Open","LatestRound":"3"},{"DivisionID":105,"Division":"FPO","DivisionName":"Women's Pro Open","Players":26,"LayoutAssignments":{"1":673557,"2":673557,"3":673557},"IsPro":true,"ShortName":"Women's Pro Open","AbbreviatedName":"Women's Pro Open","LatestRound":"3"}],"Finals":"no","HighestCompletedRound":13,"LatestRound":"3","FinalRound":3,"Layouts":[{"LayoutID":657746,"CourseID":27610,"CourseName":"Kippasuo DiscGolfPark - PRO","Name":"Championship 2024 - MPO","Holes":18,"Par":63,"Length":2788,"Units":"Meters","Accuracy":"M","Details":[{"Hole":"H1","Label":"1","Par":4,"Length":167},{"Hole":"H2","Label":"2","Par":3,"Length":95},{"Hole":"H3","Label":"3","Par":3,"Length":94},{"Hole":"H4","Label":"4","Par":3,"Length":133},{"Hole":"H5","Label":"5","Par":3,"Length":94},{"Hole":"H6","Label":"6","Par":5,"Length":252},{"Hole":"H7","Label":"7","Par":3,"Length":96},{"Hole":"H8","Label":"8","Par":4,"Length":222},{"Hole":"H9","Label":"9","Par":3,"Length":107},{"Hole":"H10","Label":"10","Par":5,"Length":276},{"Hole":"H11","Label":"11","Par":4,"Length":226},{"Hole":"H12","Label":"12","Par":4,"Length":189},{"Hole":"H13","Label":"13","Par":3,"Length":144},{"Hole":"H14","Label":"14","Par":3,"Length":155},{"Hole":"H15","Label":"15","Par":3,"Length":143},{"Hole":"H16","Label":"16","Par":4,"Length":180},{"Hole":"H17","Label":"17","Par":3,"Length":120},{"Hole":"H18","Label":"18","Par":3,"Length":95}]},{"LayoutID":673557,"CourseID":27610,"CourseName":"Kippasuo DiscGolfPark - PRO","Name":"Championship 2024 - FPO","Holes":18,"Par":66,"Length":2602,"Units":"Meters","Accuracy":"M","Details":[{"Hole":"H1","Label":"1","Par":4,"Length":167},{"Hole":"H2","Label":"2","Par":3,"Length":95},{"Hole":"H3","Label":"3","Par":3,"Length":94},{"Hole":"H4","Label":"4","Par":4,"Length":133},{"Hole":"H5","Label":"5","Par":3,"Length":94},{"Hole":"H6","Label":"6","Par":4,"Length":175},{"Hole":"H7","Label":"7","Par":3,"Length":96},{"Hole":"H8","Label":"8","Par":5,"Length":222},{"Hole":"H9","Label":"9","Par":3,"Length":92},{"Hole":"H10","Label":"10","Par":5,"Length":221},{"Hole":"H11","Label":"11","Par":5,"Length":226},{"Hole":"H12","Label":"12","Par":4,"Length":172},{"Hole":"H13","Label":"13","Par":3,"Length":122},{"Hole":"H14","Label":"14","Par":4,"Length":155},{"Hole":"H15","Label":"15","Par":3,"Length":143},{"Hole":"H16","Label":"16","Par":4,"Length":180},{"Hole":"H17","Label":"17","Par":3,"Length":120},{"Hole":"H18","Label":"18","Par":3,"Length":95}]},{"LayoutID":673559,"CourseID":27610,"CourseName":"Kippasuo DiscGolfPark - PRO","Name":"Championship 2024 - Play-off","Holes":18,"Par":60,"Length":2250,"Units":"Meters","Accuracy":"M","Details":[{"Hole":"H1","Label":"16","Par":4,"Length":160},{"Hole":"H2","Label":"17","Par":3,"Length":120},{"Hole":"H3","Label":"18","Par":3,"Length":95},{"Hole":"H4","Label":"16","Par":4,"Length":160},{"Hole":"H5","Label":"17","Par":3,"Length":120},{"Hole":"H6","Label":"18","Par":3,"Length":95},{"Hole":"H7","Label":"16","Par":4,"Length":160},{"Hole":"H8","Label":"17","Par":3,"Length":120},{"Hole":"H9","Label":"18","Par":3,"Length":95},{"Hole":"H10","Label":"16","Par":4,"Length":160},{"Hole":"H11","Label":"17","Par":3,"Length":120},{"Hole":"H12","Label":"18","Par":3,"Length":95},{"Hole":"H13","Label":"16","Par":4,"Length":160},{"Hole":"H14","Label":"17","Par":3,"Length":120},{"Hole":"H15","Label":"18","Par":3,"Length":95},{"Hole":"H16","Label":"16","Par":4,"Length":160},{"Hole":"H17","Label":"17","Par":3,"Length":120},{"Hole":"H18","Label":"18","Par":3,"Length":95}]}],"LayoutIDs":[{"1":673557,"2":673557,"3":673557,"4":0,"5":0,"6":0,"7":0,"8":0,"9":0,"10":0,"11":0,"12":0,"13":673559,"Division":"FPO","Pool":""},{"1":657746,"2":657746,"3":657746,"4":0,"5":0,"6":0,"7":0,"8":0,"9":0,"10":0,"11":0,"12":0,"13":673559,"Division":"MPO","Pool":""}],"Name":"DGPT Silver - Heinola Open powered by Kippis.org","NameHtml":"DGPT Silver - Heinola Open powered by Kippis.org","MultiLineName":{"pre":"","main":"DGPT Silver - Heinola Open","post":"powered by Kippis.org"},"MultiLineNameHtml":" \u003cspan class=\"event-name-main\"\u003eDGPT Silver - Heinola Open\u003c/span\u003e \u003cspan class=\"event-name-post\"\u003epowered by Kippis.org\u003c/span\u003e","RawTier":"A","Rounds":3,"RoundsList":{"1":{"Number":1,"Label":"Round 1","LabelAbbreviated":"Rd 1","Date":"2024-06-09","DateAbbreviated":"Jun 9","ShowDate":false},"13":{"Number":13,"Label":"Playoff","LabelAbbreviated":"P","Date":"2024-06-09","DateAbbreviated":"Jun 9","ShowDate":false},"2":{"Number":2,"Label":"Round 2","LabelAbbreviated":"Rd 2","Date":"2024-06-09","DateAbbreviated":"Jun 9","ShowDate":false},"3":{"Number":3,"Label":"Round 3","LabelAbbreviated":"Rd 3","Date":"2024-06-09","DateAbbreviated":"Jun 9","ShowDate":false}},"Semis":"no","SimpleName":"DGPT Silver - Heinola Open","StartDate":"2024-06-07","TDName":"Riku Kankaanpää","TDPDGANum":58379,"Tier":"A","FormattedTier":"A-Tier","FormattedLongTier":"A-Tier","TierPro":"A","TierAm":"A","TierX":false,"TotalPlayers":134,"TournamentId":"78666","International":true,"FullStats":true,"AdditionalEventInfo":{"RoundsList":null,"BroadcastUrl":""}},"hash":"328cfc2867217a35a44b6bf01e48e0dd"}