{"data":{"DateRange":"Feb 23-25, 2024","EndDate":"2024-02-25","Country":"United States","Location":"Brooksville, Florida","LocationShort":"Brooksville, FL","Divisions":[{"DivisionID":100,"Division":"MPO","DivisionName":"Mixed Pro Open","Players":112,"LayoutAssignments":{"1":659595,"2":656135,"3":656135},"IsPro":true,"ShortName":"Mixed Pro Open","AbbreviatedName":"Mixed Pro Open","LatestRound":"3"},{"DivisionID":105,"Division":"FPO","DivisionName":"Women's Pro Open","Players":43,"LayoutAssignments":{"1":659594,"2":658866,"3":658866},"IsPro":true,"ShortName":"Women's Pro Open","AbbreviatedName":"Women's Pro Open","LatestRound":"3"}],"Finals":"no","HighestCompletedRound":3,"LatestRound":"3","FinalRound":3,"Layouts":[{"LayoutID":656135,"CourseID":304099,"CourseName":"Olympus","Name":"Chess.com MPO","Holes":18,"Par":66,"Length":10348,"Units":"Feet","Accuracy":"M","Details":[{"Hole":"H1","Label":"1","Par":3,"Length":357},{"Hole":"H2","Label":"2","Par":4,"Length":730},{"Hole":"H3","Label":"3","Par":4,"Length":531},{"Hole":"H4","Label":"4","Par":4,"Length":664},{"Hole":"H5","Label":"5","Par":3,"Length":408},{"Hole":"H6","Label":"6","Par":4,"Length":790},{"Hole":"H7","Label":"7","Par":3,"Length":350},{"Hole":"H8","Label":"8","Par":3,"Length":487},{"Hole":"H9","Label":"9","Par":3,"Length":465},{"Hole":"H10","Label":"10","Par":3,"Length":341},{"Hole":"H11","Label":"11","Par":4,"Length":491},{"Hole":"H12","Label":"12","Par":3,"Length":563},{"Hole":"H13","Label":"13","Par":4,"Length":468},{"Hole":"H14","Label":"14","Par":4,"Length":764},{"Hole":"H15","Label":"15","Par":5,"Length":934},{"Hole":"H16","Label":"16","Par":4,"Length":737},{"Hole":"H17","Label":"17","Par":4,"Length":588},{"Hole":"H18","Label":"18","Par":4,"Length":680}]},{"LayoutID":658866,"CourseID":304099,"CourseName":"Olympus","Name":"Chess.com FPO","Holes":18,"Par":68,"Length":9464,"Units":"Feet","Accuracy":"M","Details":[{"Hole":"H1","Label":"1","Par":3,"Length":278},{"Hole":"H2","Label":"2","Par":4,"Length":625},{"Hole":"H3","Label":"3","Par":4,"Length":507},{"Hole":"H4","Label":"4","Par":4,"Length":646},{"Hole":"H5","Label":"5","Par":3,"Length":290},{"Hole":"H6","Label":"6","Par":4,"Length":671},{"Hole":"H7","Label":"7","Par":3,"Length":329},{"Hole":"H8","Label":"8","Par":3,"Length":465},{"Hole":"H9","Label":"9","Par":3,"Length":387},{"Hole":"H10","Label":"10","Par":3,"Length":308},{"Hole":"H11","Label":"11","Par":3,"Length":330},{"Hole":"H12","Label":"12","Par":4,"Length":606},{"Hole":"H13","Label":"13","Par":4,"Length":426},{"Hole":"H14","Label":"14","Par":5,"Length":900},{"Hole":"H15","Label":"15","Par":5,"Length":851},{"Hole":"H16","Label":"16","Par":4,"Length":724},{"Hole":"H17","Label":"17","Par":4,"Length":441},{"Hole":"H18","Label":"18","Par":5,"Length":680}]},{"LayoutID":659001,"CourseID":304099,"CourseName":"Olympus","Name":"Chess.com MPO Playoff","Holes":16,"Par":56,"Length":9016,"Units":"Feet","Accuracy":"M","Details":[{"Hole":"H1","Label":"18","Par":4,"Length":680},{"Hole":"H2","Label":"1","Par":3,"Length":357},{"Hole":"H3","Label":"2","Par":4,"Length":730},{"Hole":"H4","Label":"8","Par":3,"Length":487},{"Hole":"H5","Label":"18","Par":4,"Length":680},{"Hole":"H6","Label":"1","Par":3,"Length":357},{"Hole":"H7","Label":"2","Par":4,"Length":730},{"Hole":"H8","Label":"8","Par":3,"Length":487},{"Hole":"H9","Label":"18","Par":4,"Length":680},{"Hole":"H10","Label":"1","Par":3,"Length":357},{"Hole":"H11","Label":"2","Par":4,"Length":730},{"Hole":"H12","Label":"8","Par":3,"Length":487},{"Hole":"H13","Label":"18","Par":4,"Length":680},{"Hole":"H14","Label":"1","Par":3,"Length":357},{"Hole":"H15","Label":"2","Par":4,"Length":730},{"Hole":"H16","Label":"8","Par":3,"Length":487}]},{"LayoutID":659002,"CourseID":304099,"CourseName":"Olympus","Name":"Chess.com FPO Playoff","Holes":16,"Par":60,"Length":8192,"Units":"Feet","Accuracy":"M","Details":[{"Hole":"H1","Label":"18","Par":5,"Length":680},{"Hole":"H2","Label":"1","Par":3,"Length":278},{"Hole":"H3","Label":"2","Par":4,"Length":625},{"Hole":"H4","Label":"8","Par":3,"Length":465},{"Hole":"H5","Label":"18","Par":5,"Length":680},{"Hole":"H6","Label":"1","Par":3,"Length":278},{"Hole":"H7","Label":"2","Par":4,"Length":625},{"Hole":"H8","Label":"8","Par":3,"Length":465},{"Hole":"H9","Label":"18","Par":5,"Length":680},{"Hole":"H10","Label":"1","Par":3,"Length":278},{"Hole":"H11","Label":"2","Par":4,"Length":625},{"Hole":"H12","Label":"8","Par":3,"Length":465},{"Hole":"H13","Label":"18","Par":5,"Length":680},{"Hole":"H14","Label":"1","Par":3,"Length":278},{"Hole":"H15","Label":"2","Par":4,"Length":625},{"Hole":"H16","Label":"8","Par":3,"Length":465}]},{"LayoutID":659594,"CourseID":304099,"CourseName":"Olympus","Name":"Chess.com FPO Rd1","Holes":18,"Par":68,"Length":9464,"Units":"Feet","Accuracy":"M","Details":[{"Hole":"H1","Label":"1","Par":3,"Length":278},{"Hole":"H2","Label":"2","Par":4,"Length":625},{"Hole":"H3","Label":"3","Par":4,"Length":507},{"Hole":"H4","Label":"4","Par":4,"Length":646},{"Hole":"H5","Label":"5","Par":3,"Length":290},{"Hole":"H6","Label":"6","Par":4,"Length":671},{"Hole":"H7","Label":"7","Par":3,"Length":329},{"Hole":"H8","Label":"8","Par":3,"Length":465},{"Hole":"H9","Label":"9","Par":3,"Length":387},{"Hole":"H10","Label":"10","Par":3,"Length":308},{"Hole":"H11","Label":"11","Par":3,"Length":330},{"Hole":"H12","Label":"12","Par":4,"Length":606},{"Hole":"H13","Label":"13","Par":4,"Length":426},{"Hole":"H14","Label":"14","Par":5,"Length":900},{"Hole":"H15","Label":"15","Par":5,"Length":851},{"Hole":"H16","Label":"16","Par":4,"Length":724},{"Hole":"H17","Label":"17","Par":4,"Length":441},{"Hole":"H18","Label":"18","Par":5,"Length":680}]},{"LayoutID":659595,"CourseID":304099,"CourseName":"Olympus","Name":"Chess.com MPO Rd1","Holes":18,"Par":66,"Length":10348,"Units":"Feet","Accuracy":"M","Details":[{"Hole":"H1","Label":"1","Par":3,"Length":357},{"Hole":"H2","Label":"2","Par":4,"Length":730},{"Hole":"H3","Label":"3","Par":4,"Length":531},{"Hole":"H4","Label":"4","Par":4,"Length":664},{"Hole":"H5","Label":"5","Par":3,"Length":408},{"Hole":"H6","Label":"6","Par":4,"Length":790},{"Hole":"H7","Label":"7","Par":3,"Length":350},{"Hole":"H8","Label":"8","Par":3,"Length":487},{"Hole":"H9","Label":"9","Par":3,"Length":465},{"Hole":"H10","Label":"10","Par":3,"Length":341},{"Hole":"H11","Label":"11","Par":4,"Length":491},{"Hole":"H12","Label":"12","Par":3,"Length":563},{"Hole":"H13","Label":"13","Par":4,"Length":468},{"Hole":"H14","Label":"14","Par":4,"Length":764},{"Hole":"H15","Label":"15","Par":5,"Length":934},{"Hole":"H16","Label":"16","Par":4,"Length":737},{"Hole":"H17","Label":"17","Par":4,"Length":588},{"Hole":"H18","Label":"18","Par":4,"Length":680}]}],"LayoutIDs":[{"1":659594,"2":658866,"3":658866,"4":0,"5":0,"6":0,"7":0,"8":0,"9":0,"10":0,"11":0,"12":0,"13":0,"Division":"FPO","Pool":""},{"1":659595,"2":656135,"3":656135,"4":0,"5":0,"6":0,"7":0,"8":0,"9":0,"10":0,"11":0,"12":0,"13":0,"Division":"MPO","Pool":""}],"Name":"Chess.com Invitational presented by Discraft","NameHtml":"Chess.com Invitational presented by Discraft","MultiLineName":{"pre":"","main":"Chess.com Invitational","post":"presented by Discraft"},"MultiLineNameHtml":" \u003cspan class=\"event-name-main\"\u003eChess.com Invitational\u003c/span\u003e \u003cspan class=\"event-name-post\"\u003epresented by Discraft\u003c/span\u003e","RawTier":"ES","Rounds":3,"RoundsList":{"1":{"Number":1,"Label":"Round 1","LabelAbbreviated":"Rd 1","Date":"2024-02-25","DateAbbreviated":"Feb 25","ShowDate":false},"2":{"Number":2,"Label":"Round 2","LabelAbbreviated":"Rd 2","Date":"2024-02-25","DateAbbreviated":"Feb 25","ShowDate":false},"3":{"Number":3,"Label":"Round 3","LabelAbbreviated":"Rd 3","Date":"2024-02-25","DateAbbreviated":"Feb 25","ShowDate":false}},"Semis":"no","SimpleName":"DGPT - Chess.com Invitational","StartDate":"2024-02-23","TDName":"Jeffrey Korns","TDPDGANum":69287,"Tier":"Disc Golf Pro Tour","FormattedTier":"Disc Golf Pro Tour","FormattedLongTier":"Disc Golf Pro Tour","TierPro":"ES","TierAm":"ES","TierX":false,"TotalPlayers":155,"TournamentId":"77775","International":true,"FullStats":true,"AdditionalEventInfo":{"RoundsList":null,"BroadcastUrl":""}},"hash":"75b2fe9e6a942723dd376f0992a5b6fb"}